pwarp/__init__.py
pwarp/_io.py
pwarp/_np.py
pwarp/logger.py
pwarp/profiler.py
pwarp/conf/__init__.py
pwarp/conf/logging_schemas/default.json
pwarp/core/__init__.py
pwarp/core/arap.py
pwarp/core/dtype.py
pwarp/core/ops.py
pwarp/data/__init__.py
pwarp/data/frame.obj
pwarp/data/puppet.obj
pwarp/data/puppet.png
pwarp/data/puppet.py
pwarp/demo/__init__.py
pwarp/demo/demo.py
pwarp/demo/draw.py
pwarp/demo/misc.py
pwarp/mesh/__init__.py
pwarp/mesh/tri.py
pwarp/warp/__init__.py
pwarp/warp/affine.py
pwarp/warp/warp.py
puppet_warp-0.3.dist-info/LICENCE
puppet_warp-0.3.dist-info/METADATA
puppet_warp-0.3.dist-info/WHEEL
puppet_warp-0.3.dist-info/top_level.txt
puppet_warp-0.3.dist-info/RECORD
